README.md
setup.py
selenium_page_factory.egg-info/PKG-INFO
selenium_page_factory.egg-info/SOURCES.txt
selenium_page_factory.egg-info/dependency_links.txt
selenium_page_factory.egg-info/requires.txt
selenium_page_factory.egg-info/top_level.txt
seleniumpagefactory/Pagefactory.py
seleniumpagefactory/__init__.py
tests/__init__.py
tests/selenium_unitest.py
tests/test_selenium.py