Metadata-Version: 2.1
Name: selenium-page-factory
Version: 2.0
Summary: Python library provides page factory approach to implement page object model in selenium
Home-page: https://github.com/NayakwadiS/selenium-page-factory
Author: Sujit Nayakwadi
Author-email: nayakwadi.sujit@gmail.com
License: MIT
Keywords: selenium,page object model,pom,pages,page factory
Platform: UNKNOWN
